[
  { "level": 1, "q": "Какого цвета трава?", "a": "Зелёного" },
  { "level": 1, "q": "Какого цвета солнце?", "a": "Жёлтого" },
  { "level": 1, "q": "Какого цвета небо днём?", "a": "Голубого" },
  { "level": 1, "q": "Какого цвета снег?", "a": "Белого" },
  { "level": 1, "q": "Какого цвета помидор?", "a": "Красного" },
  { "level": 1, "q": "Как называется фигура с четырьмя одинаковыми сторонами?", "a": "Квадрат" },
  { "level": 1, "q": "Как называется круглая фигура?", "a": "Круг" },
  { "level": 1, "q": "Как называется фигура с тремя углами?", "a": "Треугольник" },
  { "level": 1, "q": "Какого цвета банан?", "a": "Жёлтого" },
  { "level": 1, "q": "Как называется фигура, похожая на яйцо?", "a": "Овал" },

  { "level": 2, "q": "Какой цвет получится, если смешать жёлтый и синий?", "a": "Зелёный" },
  { "level": 2, "q": "Какой цвет получится, если смешать красный и белый?", "a": "Розовый" },
  { "level": 2, "q": "Как называется фигура с пятью углами?", "a": "Пятиугольник" },
  { "level": 2, "q": "Как называется фигура без углов?", "a": "Круг" },
  { "level": 2, "q": "Какой цвет получится, если смешать синий и красный?", "a": "Фиолетовый" },
  { "level": 2, "q": "Как называется фигура с четырьмя сторонами, но не квадрат?", "a": "Прямоугольник" },
  { "level": 2, "q": "Какой цвет у апельсина?", "a": "Оранжевый" },
  { "level": 2, "q": "Какой цвет у травы летом?", "a": "Зелёный" },
  { "level": 2, "q": "Как называется фигура, похожая на мяч?", "a": "Шар" },
  { "level": 2, "q": "Какой цвет получится, если смешать красный и жёлтый?", "a": "Оранжевый" },

  { "level": 3, "q": "Как называется фигура с шестью углами?", "a": "Шестиугольник" },
  { "level": 3, "q": "Как называется фигура с восемью углами?", "a": "Восьмиугольник" },
  { "level": 3, "q": "Как называется цвет между синим и зелёным?", "a": "Бирюзовый" },
  { "level": 3, "q": "Как называется фигура в форме сердца?", "a": "Сердце" },
  { "level": 3, "q": "Какой цвет получается при смешивании всех цветов?", "a": "Коричневый" },
  { "level": 3, "q": "Какой цвет стал символом 2026 года по мнению университета цвета Panton", "a": "Белый" },
  { "level": 3, "q": "Как называется фигура с тремя одинаковыми сторонами?", "a": "Равносторонний треугольник" },
  { "level": 3, "q": "Какой цвет противоположен белому?", "a": "Чёрный" },
  { "level": 3, "q": "Как называется фигура без углов и сторон?", "a": "Круг" },
  { "level": 3, "q": "Как называется цвет ночного неба?", "a": "Тёмно-синий" }
]
